LICENSE.rst
README.md
setup.cfg
setup.py
ieseg_recsys/__init__.py
ieseg_recsys/eval.py
ieseg_recsys/model.py
ieseg_recsys/utils.py
ieseg_recsys.egg-info/PKG-INFO
ieseg_recsys.egg-info/SOURCES.txt
ieseg_recsys.egg-info/dependency_links.txt
ieseg_recsys.egg-info/requires.txt
ieseg_recsys.egg-info/top_level.txt