Metadata-Version: 2.1
Name: ieseg-recsys
Version: 0.23
Summary: Recommendation Systems - IESEG School of Management
Home-page: https://github.com/pnborchert
Author: Philipp Borchert
Author-email: p.borchert@ieseg.fr
License: MIT
Keywords: Recommender Systems IESEG
License-File: LICENSE.rst
